urbanity/__init__.py
urbanity/building.py
urbanity/building_height_data/building_grids.json
urbanity/data_class.py
urbanity/geom.py
urbanity/ghs_data/global_ghs_grid.parquet
urbanity/integration.py
urbanity/lcz_data/lcz_data.json
urbanity/map_data/GADM_links.json
urbanity/map_data/country.json
urbanity/map_data/links_general_tiled.json
urbanity/map_data/network_data.json
urbanity/map_data/poi_filter.json
urbanity/map_data/tiled_data.json
urbanity/overture_data/overture_building.json
urbanity/overture_data/overture_places.json
urbanity/population.py
urbanity/satellite.py
urbanity/svi.py
urbanity/svi_data/num_to_class.json
urbanity/svi_data/svi_data.json
urbanity/topology.py
urbanity/urbanity.py
urbanity/utils.py
urbanity/visualisation.py
urbanity-0.5.19.dist-info/LICENSE
urbanity-0.5.19.dist-info/METADATA
urbanity-0.5.19.dist-info/WHEEL
urbanity-0.5.19.dist-info/RECORD
