Metadata-Version: 2.3
Name: urbanity
Version: 0.5.19
Summary: A python package to generate urban graphs for any geographical location and scale
License: MIT
Author: winstonyym
Author-email: winstonyym@u.nus.edu
Requires-Python: >=3.9,<4.0
Classifier: License :: OSI Approved :: MIT License
Classifier: Programming Language :: Python :: 3
Classifier: Programming Language :: Python :: 3.9
Classifier: Programming Language :: Python :: 3.10
Classifier: Programming Language :: Python :: 3.11
Classifier: Programming Language :: Python :: 3.12
Classifier: Programming Language :: Python :: 3.13
Provides-Extra: osm
Requires-Dist: dotenv (>=0.9.9,<0.10.0)
Requires-Dist: geopandas (>=1.0.1,<2.0.0)
Requires-Dist: ipykernel (==6.16.2)
Requires-Dist: ipyleaflet (==0.17.2)
Requires-Dist: ipywidgets (==8.0.2)
Requires-Dist: mercantile (>=1.2.1,<2.0.0)
Requires-Dist: networkx (==2.8.6)
Requires-Dist: numpy (==1.26.4)
Requires-Dist: pandas (>=2.2.2,<3.0.0)
Requires-Dist: protobuf (==3.20.0) ; extra == "osm"
Requires-Dist: pydeck (>=0.9.1,<0.10.0)
Requires-Dist: pyrobuf (>=0.9.3,<0.10.0) ; extra == "osm"
Requires-Dist: pyrosm (==0.6.2) ; extra == "osm"
Requires-Dist: rasterio (>=1.3.8,<2.0.0)
